benchmark.py
entropy_analyzer.py
hubris.py
hubris_fp_filter.py
lang_analyzers.py
olympus.py
oracle.py
prometheus.py
prometheus_ui.py
scent_analyzer.py
sentinel.py
shield_analyzer.py
prometheus_analyzer/__init__.py
prometheus_analyzer/_version.py
prometheus_analyzer-0.1.0.dist-info/licenses/LICENSE
prometheus_analyzer-0.1.0.dist-info/METADATA
prometheus_analyzer-0.1.0.dist-info/WHEEL
prometheus_analyzer-0.1.0.dist-info/entry_points.txt
prometheus_analyzer-0.1.0.dist-info/top_level.txt
prometheus_analyzer-0.1.0.dist-info/RECORD
