Metadata-Version: 2.4
Name: prometheus-analyzer
Version: 0.1.0
Summary: Complexity Fitness Analyzer for Codebases - Measures whether your codebase is more complex than it needs to be
Author-email: "Andrew H. Bond" <andrew.bond@sjsu.edu>
License-Expression: MIT
Project-URL: Homepage, https://github.com/yourusername/prometheus
Project-URL: Documentation, https://github.com/yourusername/prometheus#readme
Project-URL: Repository, https://github.com/yourusername/prometheus
Project-URL: Issues, https://github.com/yourusername/prometheus/issues
Keywords: complexity,code-quality,resilience,fitness,analyzer,metrics
Classifier: Development Status :: 4 - Beta
Classifier: Intended Audience :: Developers
Classifier: Programming Language :: Python :: 3
Classifier: Programming Language :: Python :: 3.8
Classifier: Programming Language :: Python :: 3.9
Classifier: Programming Language :: Python :: 3.10
Classifier: Programming Language :: Python :: 3.11
Classifier: Programming Language :: Python :: 3.12
Classifier: Topic :: Software Development :: Quality Assurance
Classifier: Topic :: Software Development :: Testing
Classifier: Topic :: Software Development :: Libraries :: Python Modules
Requires-Python: >=3.8
License-File: LICENSE
Requires-Dist: radon>=5.1.0
Requires-Dist: lizard>=1.17.0
Provides-Extra: security
Requires-Dist: bandit>=1.7.0; extra == "security"
Provides-Extra: full
Requires-Dist: radon>=5.1.0; extra == "full"
Requires-Dist: lizard>=1.17.0; extra == "full"
Requires-Dist: bandit>=1.7.0; extra == "full"
Dynamic: license-file
